MANIFEST.in
l10n_syscohada_data.xml
l10n_syscohada_wizard.xml
setup.py
./__init__.py
./__openerp__.py
i18n/ar.po
i18n/ca.po
i18n/es.po
i18n/es_CR.po
i18n/es_MX.po
i18n/es_VE.po
i18n/fr.po
i18n/fr_FR.po
i18n/l10n_syscohada.pot
i18n/nl.po
i18n/pt.po
i18n/pt_BR.po
i18n/ro.po
i18n/sl.po
i18n/tr.po
openerp_l10n_syscohada.egg-info/PKG-INFO
openerp_l10n_syscohada.egg-info/SOURCES.txt
openerp_l10n_syscohada.egg-info/dependency_links.txt
openerp_l10n_syscohada.egg-info/requires.txt
openerp_l10n_syscohada.egg-info/top_level.txt